dockumentor/__init__.py
dockumentor/dockumentor.py
dockumentor/templates/dockumentor_compose.md
dockumentor-0.1.2.dist-info/METADATA
dockumentor-0.1.2.dist-info/WHEEL
dockumentor-0.1.2.dist-info/entry_points.txt
dockumentor-0.1.2.dist-info/RECORD
