Metadata-Version: 2.1
Name: dockumentor
Version: 0.1.2
Summary: Dockumentor is a Python utility that automates the generation of detailed documentation for Docker Compose projects. It interprets Docker Compose configurations to produce visual diagrams and markdown documentation, leveraging Mermaid diagrams and Jinja2 templates to provide clear and customizable representations of service architectures. Ideal for development teams and educators, Dockumentor streamlines the process of maintaining accurate and visual documentation for Docker environment
License: MIT
Author: Lucian BLETAN
Author-email: neuraluc@gmail.com
Requires-Python: >=3.8,<4.0
Classifier: License :: OSI Approved :: MIT License
Classifier: Programming Language :: Python :: 3
Classifier: Programming Language :: Python :: 3.8
Classifier: Programming Language :: Python :: 3.9
Classifier: Programming Language :: Python :: 3.10
Classifier: Programming Language :: Python :: 3.11
Classifier: Programming Language :: Python :: 3.12
Classifier: Programming Language :: Python :: 3.13
Requires-Dist: Jinja2 (>=3.1.4,<4.0.0)
Requires-Dist: PyYAML (>=6.0.1,<7.0.0)
Requires-Dist: click (>=8.1.7,<9.0.0)
